tranquillo_staking_api/__init__.py
tranquillo_staking_api/colossus_client.py
tranquillo_staking_api/colossus_exceptions.py
tranquillo_staking_api/endpoint_server.py
tranquillo_staking_api/mongo_client.py
tranquillo_staking_api/tester.py
tranquillo_staking_api-0.1.3.dist-info/METADATA
tranquillo_staking_api-0.1.3.dist-info/WHEEL
tranquillo_staking_api-0.1.3.dist-info/RECORD
