Metadata-Version: 2.1
Name: tranquillo_staking_api
Version: 0.1.3
Summary: A Python SDK for interacting with the Tranquillo API
Author: Raj Panesar
Author-email: raj@itranquillo.digital
Requires-Python: >=3.11,<4.0
Classifier: Programming Language :: Python :: 3
Classifier: Programming Language :: Python :: 3.11
Requires-Dist: flask (>=3.0.0,<4.0.0)
Requires-Dist: pymongo (>=4.6.1,<5.0.0)
Requires-Dist: requests (>=2.31.0,<3.0.0)
